cluster_search/__init__.py
cluster_search/_modidx.py
cluster_search/cluser_grid_search.py
cluster_search/cluster-search.py
cluster_search/cluster_grid_search.py
cluster_search/cluster_search.py
cluster_search/core.py
cluster_search-0.0.2.dist-info/LICENSE
cluster_search-0.0.2.dist-info/METADATA
cluster_search-0.0.2.dist-info/WHEEL
cluster_search-0.0.2.dist-info/entry_points.txt
cluster_search-0.0.2.dist-info/top_level.txt
cluster_search-0.0.2.dist-info/RECORD
