Metadata-Version: 2.1
Name: cluster-search
Version: 0.0.2
Summary: Python package to cluster data
Home-page: https://github.com/Jack-0-0/cluster-search/
Author: Jack Rasala
Author-email: jack.rasala@nesta.org.uk
License: Apache Software License 2.0
Keywords: clustering nbdev
Classifier: Development Status :: 3 - Alpha
Classifier: Intended Audience :: Developers
Classifier: Natural Language :: English
Classifier: Programming Language :: Python :: 3.9
Classifier: Programming Language :: Python :: 3.10
Classifier: License :: OSI Approved :: Apache Software License
Requires-Python: >=3.9
License-File: LICENSE
Requires-Dist: scikit-learn
Requires-Dist: pandas
Requires-Dist: tqdm
Requires-Dist: Jinja2
Provides-Extra: dev
